{"cameraMode":{"drawMode":0,"name":"Shaded","section":"Shading Mode"},"sceneLighting":false,"audioPlay":false,"sceneViewState":{"showFog":true,"showMaterialUpdate":false,"showSkybox":false,"showFlares":true,"showImageEffects":true,"showParticleSystems":true},"in2DMode":false,"pivot":{"x":-16.096887588500978,"y":20.311878204345704,"z":22.979421615600587},"rotation":{"x":-0.0625443235039711,"y":-0.6521717309951782,"z":0.05413011834025383,"w":-0.7535531520843506},"size":2.0090043544769289,"orthographic":false}